AUTHORS.rst
CONTRIBUTING.rst
HISTORY.rst
LICENSE
MANIFEST.in
README.rst
setup.cfg
setup.py
docs/Makefile
docs/authors.rst
docs/conf.py
docs/contributing.rst
docs/history.rst
docs/index.rst
docs/installation.rst
docs/make.bat
docs/readme.rst
docs/usage.rst
docs/modules/adwords.rst
easyadwords/__init__.py
easyadwords/adwords.py
easyadwords/utils.py
easyadwords.egg-info/PKG-INFO
easyadwords.egg-info/SOURCES.txt
easyadwords.egg-info/dependency_links.txt
easyadwords.egg-info/not-zip-safe
easyadwords.egg-info/requires.txt
easyadwords.egg-info/top_level.txt