Metadata-Version: 1.1
Name: easyadwords
Version: 0.1.3
Summary: User friendly wrapper for Google AdWords
Home-page: https://github.com/danielpoonwj/easyadwords
Author: Daniel Poon
Author-email: daniel.poon.wenjie@gmail.com
License: Apache Software License 2.0
Keywords: google,adwords,wrapper
Platform: UNKNOWN
Classifier: Development Status :: 2 - Pre-Alpha
Classifier: Intended Audience :: Developers
Classifier: License :: OSI Approved :: Apache Software License
Classifier: Natural Language :: English
Classifier: Programming Language :: Python :: 2
Classifier: Programming Language :: Python :: 2.6
Classifier: Programming Language :: Python :: 2.7
